ssrm_test/__init__.py
ssrm_test/constants.py
ssrm_test/ssrm_test.py
ssrm_test/test_jupyter_notebooks.py
ssrm_test/test_ssrm_test.py
ssrm_test-0.1.5.dist-info/LICENSE
ssrm_test-0.1.5.dist-info/WHEEL
ssrm_test-0.1.5.dist-info/METADATA
ssrm_test-0.1.5.dist-info/RECORD
