Metadata-Version: 2.1
Name: ssrm-test
Version: 0.1.5
Summary: A library for Sequential Sample Ratio Mismatch (SRM) test.
Home-page: https://github.com/optimizely/ssrm
License: Apache-2.0
Author: Michael Lindon
Author-email: michael.lindon@optimizely.com
Requires-Python: >=3.6,<4.0
Classifier: License :: OSI Approved :: Apache Software License
Classifier: Programming Language :: Python :: 3
Classifier: Programming Language :: Python :: 3.6
Classifier: Programming Language :: Python :: 3.7
Classifier: Programming Language :: Python :: 3.8
Requires-Dist: numpy (>=1.16,<2.0)
Requires-Dist: scipy (>=1.3,<2.0)
Requires-Dist: toolz (>=0.10.0,<0.11.0)
Requires-Dist: typing (>=3.7.4,<4.0.0)
Project-URL: Repository, https://github.com/optimizely/ssrm
